.gitignore
.travis.yml
CHANGES.rst
LICENSE
README.md
pytest.ini
release.sh
setup.py
test-requirements.txt
tox.ini
pyramid_datadog/__init__.py
pyramid_datadog.egg-info/PKG-INFO
pyramid_datadog.egg-info/SOURCES.txt
pyramid_datadog.egg-info/dependency_links.txt
pyramid_datadog.egg-info/not-zip-safe
pyramid_datadog.egg-info/requires.txt
pyramid_datadog.egg-info/top_level.txt
tests/test_includeme.py